APPLEE/__init__.py
APPLEE/functions.py
APPLEE/ld_fir.py
APPLEE/ld_postprocessing.py
APPLEE/ld_preprocessing.py
APPLEE/low_prep.py
APPLEE/test_low_pre.py
APPLEE/Utils/__init__.py
APPLEE/Utils/check_txt.py
APPLEE/Utils/delete_signals.py
APPLEE/Utils/rename_raw.py
APPLEE/Utils/utils.py
APPLEE/pipeline_stages/MyNoisyChannels.py
APPLEE/pipeline_stages/__init__.py
APPLEE/pipeline_stages/linearFIR.py
APPLEE/pipeline_stages/mypyprep.py
APPLEE/pipeline_stages/myrefence.py
APPLEE-1.2.dist-info/METADATA
APPLEE-1.2.dist-info/WHEEL
APPLEE-1.2.dist-info/top_level.txt
APPLEE-1.2.dist-info/RECORD
