Metadata-Version: 2.1
Name: APPLEE
Version: 1.2
Home-page: https://github.com/GRUNECO/portables.git
Author: 
Author-email: 
